torqueclient/__init__.py
torqueclient/api.py
torqueclient/cache.py
torqueclient/version.py
torqueclient-0.8.3.dist-info/licenses/LICENSE.md
torqueclient-0.8.3.dist-info/METADATA
torqueclient-0.8.3.dist-info/WHEEL
torqueclient-0.8.3.dist-info/top_level.txt
torqueclient-0.8.3.dist-info/RECORD
