Metadata-Version: 2.4
Name: torqueclient
Version: 0.8.3
Summary: Python client for mediawiki/torque
Home-page: https://code.librehq.com/ots/mediawiki/torque
Author: Open Tech Strategies, LLC
Author-email: frankduncan@opentechstrategies.com
Classifier: Programming Language :: Python :: 3
Classifier: License :: OSI Approved :: GNU Affero General Public License v3
Classifier: Operating System :: OS Independent
License-File: LICENSE.md
Requires-Dist: mwclient
Requires-Dist: python-dateutil
Dynamic: author
Dynamic: author-email
Dynamic: classifier
Dynamic: description
Dynamic: description-content-type
Dynamic: home-page
Dynamic: license-file
Dynamic: requires-dist
Dynamic: summary
